edgegap_factory/__init__.py
edgegap_factory/_base_factory.py
edgegap_factory/_generator.py
edgegap_factory/_sql_model_factory.py
edgegap_factory-1.9.12.dist-info/METADATA
edgegap_factory-1.9.12.dist-info/WHEEL
edgegap_factory-1.9.12.dist-info/RECORD
