Metadata-Version: 2.1
Name: edgegap-factory
Version: 1.9.12
Summary: Edgegap library for creating SqlModel
Author: Maxime Boisvert
Author-email: maxime.boisvert@edgegap.com
Requires-Python: >=3.10,<4.0
Classifier: Programming Language :: Python :: 3
Classifier: Programming Language :: Python :: 3.10
Classifier: Programming Language :: Python :: 3.11
Classifier: Programming Language :: Python :: 3.12
Requires-Dist: sqlalchemy (>=2.0.0,<3.0.0)
Requires-Dist: sqlmodel (>=0.0.22,<0.0.23)
